django_template_field-0.2.0.dist-info/DESCRIPTION.rst
django_template_field-0.2.0.dist-info/METADATA
django_template_field-0.2.0.dist-info/RECORD
django_template_field-0.2.0.dist-info/WHEEL
django_template_field-0.2.0.dist-info/metadata.json
django_template_field-0.2.0.dist-info/top_level.txt
templatefield/__init__.py
templatefield/fields.py
templatefield/managers.py
templatefield/settings.py
templatefield/test/__init__.py
templatefield/test/models.py
templatefield/test/settings.py
templatefield/test/test_fields.py
