Metadata-Version: 2.0
Name: django-template-field
Version: 0.2.0
Summary: A Django fitemplate field twith managers to return the rendered or unrendered template.
Home-page: https://github.com/orcasgit/django-template-field
Author: Jess Johnson
Author-email: jess@grokcode.com
License: BSD
Keywords: django-template-field
Platform: UNKNOWN
Classifier: Development Status :: 3 - Alpha
Classifier: Framework :: Django
Classifier: Framework :: Django :: 1.7
Classifier: Framework :: Django :: 1.8
Classifier: Intended Audience :: Developers
Classifier: License :: OSI Approved :: BSD License
Classifier: Natural Language :: English
Classifier: Programming Language :: Python :: 2
Classifier: Programming Language :: Python :: 2.7
Classifier: Programming Language :: Python :: 3
Classifier: Programming Language :: Python :: 3.3
Classifier: Programming Language :: Python :: 3.4
Classifier: Programming Language :: Python :: 3.5
